ShenduXuexiJiaocheng01LisaShiyanshi20170304/README.md
ShenduXuexiJiaocheng01LisaShiyanshi20170304/__init__.py
ShenduXuexiJiaocheng01LisaShiyanshi20170304/__main__.py
ShenduXuexiJiaocheng01LisaShiyanshi20170304/file.epub
ShenduXuexiJiaocheng01LisaShiyanshi20170304/index.html
ShenduXuexiJiaocheng01LisaShiyanshi20170304/css/__init__.py
ShenduXuexiJiaocheng01LisaShiyanshi20170304/css/annotations.css
ShenduXuexiJiaocheng01LisaShiyanshi20170304/css/main.css
ShenduXuexiJiaocheng01LisaShiyanshi20170304/css/normalize.css
ShenduXuexiJiaocheng01LisaShiyanshi20170304/css/popup.css
ShenduXuexiJiaocheng01LisaShiyanshi20170304/font/__init__.py
ShenduXuexiJiaocheng01LisaShiyanshi20170304/font/fontello.eot
ShenduXuexiJiaocheng01LisaShiyanshi20170304/font/fontello.svg
ShenduXuexiJiaocheng01LisaShiyanshi20170304/font/fontello.ttf
ShenduXuexiJiaocheng01LisaShiyanshi20170304/font/fontello.woff
ShenduXuexiJiaocheng01LisaShiyanshi20170304/img/__init__.py
ShenduXuexiJiaocheng01LisaShiyanshi20170304/img/annotator-glyph-sprite.png
ShenduXuexiJiaocheng01LisaShiyanshi20170304/img/annotator-icon-sprite.png
ShenduXuexiJiaocheng01LisaShiyanshi20170304/img/apple-touch-icon.png
ShenduXuexiJiaocheng01LisaShiyanshi20170304/img/cancelfullscreen.png
ShenduXuexiJiaocheng01LisaShiyanshi20170304/img/close.png
ShenduXuexiJiaocheng01LisaShiyanshi20170304/img/fullscreen.png
ShenduXuexiJiaocheng01LisaShiyanshi20170304/img/loader.gif
ShenduXuexiJiaocheng01LisaShiyanshi20170304/img/menu-icon.png
ShenduXuexiJiaocheng01LisaShiyanshi20170304/img/save.png
ShenduXuexiJiaocheng01LisaShiyanshi20170304/img/saved.png
ShenduXuexiJiaocheng01LisaShiyanshi20170304/img/settings-s.png
ShenduXuexiJiaocheng01LisaShiyanshi20170304/img/settings.png
ShenduXuexiJiaocheng01LisaShiyanshi20170304/img/star.png
ShenduXuexiJiaocheng01LisaShiyanshi20170304/js/__init__.py
ShenduXuexiJiaocheng01LisaShiyanshi20170304/js/epub.js
ShenduXuexiJiaocheng01LisaShiyanshi20170304/js/epub.min.js
shendu_xuexi_jiaocheng_0_1_lisa_shiyanshi_20170304-2024.3.2.0.dist-info/METADATA
shendu_xuexi_jiaocheng_0_1_lisa_shiyanshi_20170304-2024.3.2.0.dist-info/WHEEL
shendu_xuexi_jiaocheng_0_1_lisa_shiyanshi_20170304-2024.3.2.0.dist-info/entry_points.txt
shendu_xuexi_jiaocheng_0_1_lisa_shiyanshi_20170304-2024.3.2.0.dist-info/top_level.txt
shendu_xuexi_jiaocheng_0_1_lisa_shiyanshi_20170304-2024.3.2.0.dist-info/RECORD
